gunfolds/__init__.py
gunfolds/conversions.py
gunfolds/data/allloops.zkl
gunfolds/data/circular_p.zkl
gunfolds/data/colors.zkl
gunfolds/data/testgraphs.py
gunfolds/estimation/__init__.py
gunfolds/estimation/grangercausality.py
gunfolds/estimation/linear_model.py
gunfolds/estimation/pc.py
gunfolds/figures/shipfig.tex
gunfolds/figures/shippage.sty
gunfolds/solvers/__init__.py
gunfolds/solvers/clingo_msl.py
gunfolds/solvers/clingo_rasl.py
gunfolds/solvers/traversal.py
gunfolds/solvers/unknownrate.py
gunfolds/utils/__init__.py
gunfolds/utils/bfutils.py
gunfolds/utils/calc_procs.py
gunfolds/utils/clingo.py
gunfolds/utils/comparison.py
gunfolds/utils/ecj.py
gunfolds/utils/graphkit.py
gunfolds/utils/myTimeout.py
gunfolds/utils/neighborhoods.py
gunfolds/utils/simpleloops.py
gunfolds/utils/zickle.py
gunfolds/viz/__init__.py
gunfolds/viz/dbn2latex.py
gunfolds/viz/gtool.py
tests/__init__.py
tests/tests.py
gunfolds-0.11.dist-info/LICENSE
gunfolds-0.11.dist-info/METADATA
gunfolds-0.11.dist-info/WHEEL
gunfolds-0.11.dist-info/top_level.txt
gunfolds-0.11.dist-info/RECORD
