Metadata-Version: 2.1
Name: gunfolds
Version: 0.11
Summary: Tools to explore dynamic causal graphs in the case of undersampled data
Author: Sergey Plis, Cynthia Freeman, Ian Beaver
Author-email: splis@mrn.org
License: GPL
License-File: LICENSE
Requires-Dist: networkx
Requires-Dist: igraph
Requires-Dist: scipy
Requires-Dist: numpy
Requires-Dist: statsmodels
Requires-Dist: sympy
Requires-Dist: seaborn
Requires-Dist: pandas
Requires-Dist: matplotlib
Requires-Dist: progressbar
Requires-Dist: ipdb
Requires-Dist: pydot
